rank_llm/__init__.py
rank_llm/data.py
rank_llm/retrieve_and_rerank.py
rank_llm/analysis/__init__.py
rank_llm/analysis/estimate_costs.py
rank_llm/analysis/response_analysis.py
rank_llm/evaluation/__init__.py
rank_llm/evaluation/trec_eval.py
rank_llm/rerank/__init__.py
rank_llm/rerank/api_keys.py
rank_llm/rerank/identity_reranker.py
rank_llm/rerank/inference_handler.py
rank_llm/rerank/rankllm.py
rank_llm/rerank/reranker.py
rank_llm/rerank/vllm_handler.py
rank_llm/rerank/listwise/__init__.py
rank_llm/rerank/listwise/listwise_inference_handler.py
rank_llm/rerank/listwise/listwise_rankllm.py
rank_llm/rerank/listwise/lit5_reranker.py
rank_llm/rerank/listwise/multiturn_listwise_inference_handler.py
rank_llm/rerank/listwise/rank_fid.py
rank_llm/rerank/listwise/rank_gemini.py
rank_llm/rerank/listwise/rank_gpt.py
rank_llm/rerank/listwise/rank_listwise_os_llm.py
rank_llm/rerank/listwise/rankfid_inference_handler.py
rank_llm/rerank/listwise/singleturn_listwise_inference_handler.py
rank_llm/rerank/listwise/vicuna_reranker.py
rank_llm/rerank/listwise/zephyr_reranker.py
rank_llm/rerank/listwise/lit5/__init__.py
rank_llm/rerank/listwise/lit5/model.py
rank_llm/rerank/listwise/lit5/modeling_t5.py
rank_llm/rerank/pairwise/__init__.py
rank_llm/rerank/pairwise/duot5.py
rank_llm/rerank/pairwise/pairwise_inference_handler.py
rank_llm/rerank/pairwise/pairwise_rankllm.py
rank_llm/rerank/pointwise/__init__.py
rank_llm/rerank/pointwise/monot5.py
rank_llm/rerank/pointwise/pointwise_inference_handler.py
rank_llm/rerank/pointwise/pointwise_rankllm.py
rank_llm/rerank/prompt_templates/__init__.py
rank_llm/rerank/prompt_templates/duot5_template.yaml
rank_llm/rerank/prompt_templates/insert_rank_template.yaml
rank_llm/rerank/prompt_templates/monot5_template.yaml
rank_llm/rerank/prompt_templates/qwen_thinking_template.yaml
rank_llm/rerank/prompt_templates/rank_fid_score_template.yaml
rank_llm/rerank/prompt_templates/rank_fid_template.yaml
rank_llm/rerank/prompt_templates/rank_gpt_apeer_template.yaml
rank_llm-0.25.6.dist-info/licenses/LICENSE
rank_llm-0.25.6.dist-info/METADATA
rank_llm-0.25.6.dist-info/WHEEL
rank_llm-0.25.6.dist-info/top_level.txt
rank_llm-0.25.6.dist-info/RECORD
