Metadata-Version: 2.4
Name: rank-llm
Version: 0.25.6
Summary: A Package for reranking with LLMs (pointwise, pairwise, and listwise)
Author-email: Sahel Sharifymoghaddam <sahel.sharifymoghaddam@uwaterloo.ca>, Ronak Pradeep <rpradeep@uwaterloo.ca>, Jimmy Lin <jimmylin@uwaterloo.ca>
License: 
Project-URL: Homepage, https://github.com/castorini/rank_llm
Keywords: prompt-decoder,RankVicuna,RankZephyr,RankLLM,information retrieval,neural ranking,LLM,listwise,pointwise,FirstMistral
Classifier: Programming Language :: Python
Classifier: Programming Language :: Python :: 3
Requires-Python: >=3.11
License-File: LICENSE
Requires-Dist: tqdm>=4.66.2
Requires-Dist: openai>=1.23.6
Requires-Dist: tiktoken>=0.6.0
Requires-Dist: transformers>=4.40.1
Requires-Dist: python-dotenv>=1.0.1
Requires-Dist: faiss-cpu>=1.8.0
Requires-Dist: ftfy>=6.2.0
Requires-Dist: dacite>=1.8.1
Requires-Dist: vllm>=0.4.0
Requires-Dist: pandas>=1.4.0
Provides-Extra: sglang
Requires-Dist: sglang[all]~=0.4.0; extra == "sglang"
Provides-Extra: tensorrt-llm
Requires-Dist: tensorrt-llm[all]>=0.14.0; extra == "tensorrt-llm"
Provides-Extra: genai
Requires-Dist: google-generativeai>=0.8.2; extra == "genai"
Provides-Extra: pyserini
Requires-Dist: pyserini==1.2.0; extra == "pyserini"
Provides-Extra: training
Requires-Dist: accelerate>=0.34.2; extra == "training"
Requires-Dist: bitsandbytes>=0.44.1; extra == "training"
Requires-Dist: datasets>=3.0.1; extra == "training"
Requires-Dist: deepspeed>=0.15.1; extra == "training"
Requires-Dist: six>=1.16.0; extra == "training"
Requires-Dist: torch>=2.4.0; extra == "training"
Requires-Dist: numpy>=1.26.4; extra == "training"
Provides-Extra: all
Requires-Dist: rank-llm[genai]; extra == "all"
Requires-Dist: rank-llm[pyserini]; extra == "all"
Dynamic: license-file
